cli_ide/__init__.py
cli_ide/app.py
cli_ide/exceptions.py
cli_ide/py.typed
cli_ide/utils.py
cli_ide/config/__init__.py
cli_ide/config/defaults.py
cli_ide/config/settings.py
cli_ide/models/__init__.py
cli_ide/models/state.py
cli_ide/themes/__init__.py
cli_ide/themes/light.py
cli_ide/widgets/__init__.py
cli_ide/widgets/dialogs.py
cli_ide/widgets/editor.py
cli_ide/widgets/file_tree.py
cli_ide/widgets/search.py
cli_ide/widgets/terminal.py
cli_ide-0.1.0.dist-info/METADATA
cli_ide-0.1.0.dist-info/WHEEL
cli_ide-0.1.0.dist-info/entry_points.txt
cli_ide-0.1.0.dist-info/licenses/LICENSE
cli_ide-0.1.0.dist-info/RECORD
