Metadata-Version: 2.4
Name: cli-ide
Version: 0.1.0
Summary: Terminal-based IDE with file explorer, code editor, and terminal
Project-URL: Homepage, https://cli-ide.vercel.app
Project-URL: Repository, https://github.com/wojacklabs/cli-ide
Project-URL: Issues, https://github.com/wojacklabs/cli-ide/issues
Author-email: wojacklabs <wojacklabs@users.noreply.github.com>
License: MIT License
License-File: LICENSE
Keywords: editor,ide,terminal,textual,tui
Classifier: Development Status :: 3 - Alpha
Classifier: Environment :: Console
Classifier: Intended Audience :: Developers
Classifier: License :: OSI Approved :: MIT License
Classifier: Operating System :: MacOS
Classifier: Operating System :: POSIX :: Linux
Classifier: Programming Language :: Python :: 3
Classifier: Programming Language :: Python :: 3.11
Classifier: Programming Language :: Python :: 3.12
Classifier: Topic :: Text Editors :: Integrated Development Environments (IDE)
Classifier: Typing :: Typed
Requires-Python: >=3.11
Requires-Dist: pyte>=0.8.0
Requires-Dist: textual>=0.89.0
Requires-Dist: tree-sitter-languages>=1.10.0
Requires-Dist: tree-sitter>=0.23.0
Provides-Extra: dev
Requires-Dist: pytest-asyncio>=0.23.0; extra == 'dev'
Requires-Dist: pytest-cov>=4.1.0; extra == 'dev'
Requires-Dist: pytest>=8.0.0; extra == 'dev'
